LICENSE
README.md
setup.py
cursepy/__init__.py
cursepy/errors.py
cursepy/formatters.py
cursepy/proto.py
cursepy/wrapper.py
cursepy.egg-info/PKG-INFO
cursepy.egg-info/SOURCES.txt
cursepy.egg-info/dependency_links.txt
cursepy.egg-info/top_level.txt
cursepy/classes/__init__.py
cursepy/classes/base.py
cursepy/classes/search.py
cursepy/handlers/__init__.py
cursepy/handlers/base.py
cursepy/handlers/curseforge.py
cursepy/handlers/cursetools.py
cursepy/handlers/forgesvc.py
cursepy/handlers/maps.py
cursepy/handlers/metacf.py
cursepy/handlers/modrinth.py