Metadata-Version: 2.1
Name: cursepy
Version: 2.1.0
Summary: CurseForge API written in python
Home-page: https://github.com/Owen-Cochell/cursepy
Author: Owen Cochell
Author-email: owencochell@hotmail.com
Project-URL: Bug Reports, https://github.com/Owen-Cochell/cursepy/issues
Project-URL: Source, https://github.com/Owen-Cochell/cursepy
Project-URL: Documentation, https://cursepy.readthedocs.io/
Keywords: curseforge,api,curseforge-api
Classifier: Development Status :: 5 - Production/Stable
Classifier: Intended Audience :: Developers
Classifier: Topic :: Software Development :: Libraries
Classifier: License :: OSI Approved :: MIT License
Classifier: Operating System :: OS Independent
Classifier: Programming Language :: Python :: 3.7
Classifier: Programming Language :: Python :: 3.8
Classifier: Programming Language :: Python :: 3 :: Only
Requires-Python: >=3.7, <4
License-File: LICENSE
